{"name":"fbsql_result","purpose":"Get result data","manualid":"function.fbsql-result","version":"PHP 4 >= 4.0.6, PHP 5","params":[{"name":"result","type":"resource","optional":"false"},{"name":"row","type":"int","optional":"true"},{"name":"field","type":"mixed","optional":"true"}],"return":{"type":"mixed","description":""},"errors":null,"notes":[],"changelog":[],"seealso":[{"type":"function","name":"fbsql_fetch_row"},{"type":"function","name":"fbsql_fetch_array"},{"type":"function","name":"fbsql_fetch_assoc"},{"type":"function","name":"fbsql_fetch_object"}]}