{"name":"fbsql_create_clob","purpose":"Create a CLOB","manualid":"function.fbsql-create-clob","version":"PHP 4 >= 4.2.0, PHP 5","params":[{"name":"clob_data","type":"string","optional":"false"},{"name":"link_identifier","type":"resource","optional":"true"}],"return":{"type":"string","description":"Returns a resource handle to the newly created CLOB, which can be used\n   with insert and update commands to store the CLOB in the database."},"errors":null,"notes":[],"changelog":[],"seealso":[{"type":"function","name":"fbsql_create_blob"},{"type":"function","name":"fbsql_read_blob"},{"type":"function","name":"fbsql_read_clob"},{"type":"function","name":"fbsql_set_lob_mode"}]}