{"name":"openssl_sign","purpose":"Generate signature","manualid":"function.openssl-sign","version":"PHP 4 >= 4.0.4, PHP 5","params":[{"name":"data","type":"string","optional":"false"},{"name":"signature","type":"string","optional":"false"},{"name":"priv_key_id","type":"mixed","optional":"false"},{"name":"signature_alg","type":"int","optional":"true","initializer":"OPENSSL_ALGO_SHA1"}],"return":{"type":"bool","description":"Returns TRUE on success or FALSE on failure."},"errors":null,"notes":[],"changelog":[{"version":"5.0.0","change":"The signature_alg parameter was added."}],"seealso":[{"type":"function","name":"openssl_verify"}]}