{"name":"GearmanClient.doLowBackground","purpose":"Run a low priority task in the background","manualid":"gearmanclient.dolowbackground","version":false,"params":[{"name":"function_name","type":"string","optional":"false"},{"name":"workload","type":"string","optional":"false"},{"name":"unique","type":"string","optional":"true"}],"return":{"type":"string","description":"The job handle for the submitted task."},"errors":null,"notes":[],"changelog":[],"seealso":[{"type":"methodname","name":"GearmanClient::do"},{"type":"methodname","name":"GearmanClient::doHigh"},{"type":"methodname","name":"GearmanClient::doLow"},{"type":"methodname","name":"GearmanClient::doBackground"},{"type":"methodname","name":"GearmanClient::doHighBackground"}]}