{"name":"SimpleXMLElement.registerXPathNamespace","purpose":"Creates a prefix\/ns context for the next XPath query","manualid":"simplexmlelement.registerXPathNamespace","version":false,"params":[{"name":"prefix","type":"string","optional":"false"},{"name":"ns","type":"string","optional":"false"}],"return":{"type":"bool","description":"Returns TRUE on success or FALSE on failure."},"errors":null,"notes":[],"changelog":[],"seealso":[{"type":"methodname","name":"SimpleXMLElement::getDocNamespaces"},{"type":"methodname","name":"SimpleXMLElement::getNamespaces"}]}