{"name":"iconv_strpos","purpose":"Finds position of first occurrence of a needle within a haystack","manualid":"function.iconv-strpos","version":"PHP 5","params":[{"name":"haystack","type":"string","optional":"false"},{"name":"needle","type":"string","optional":"false"},{"name":"offset","type":"int","optional":"true"},{"name":"charset","type":"string","optional":"true","initializer":"ini_set(\"iconv.internal_encoding\")"}],"return":{"type":"int","description":"Returns the numeric position of the first occurrence of\n   needle in haystack.If needle is not found,\n   iconv_strpos will return FALSE.This function may\nreturn Boolean FALSE, but may also return a non-Boolean value which\nevaluates to FALSE, such as 0 or\n\"\". Please read the section on Booleans for more\ninformation. Use the ===\noperator for testing the return value of this\nfunction."},"errors":null,"notes":[],"changelog":[],"seealso":[{"type":"function","name":"strpos"},{"type":"function","name":"iconv_strrpos"},{"type":"function","name":"mb_strpos"}]}