{"name":"db2_stmt_error","purpose":"Returns a string containing the SQLSTATE returned by an SQL statement","manualid":"function.db2-stmt-error","version":"PECL ibm_db2 >= 1.0.0","params":[{"name":"stmt","type":"resource","optional":"true"}],"return":{"type":"string","description":"Returns a string containing an SQLSTATE value."},"errors":null,"notes":[],"changelog":[],"seealso":[{"type":"function","name":"db2_conn_error"},{"type":"function","name":"db2_conn_errormsg"},{"type":"function","name":"db2_stmt_errormsg"}]}