{"name":"dbplus_restorepos","purpose":"Restore position","manualid":"function.dbplus-restorepos","version":"PHP 4 <= 4.1.0, PECL dbplus >= 0.9","params":[{"name":"relation","type":"resource","optional":"false"},{"name":"tuple","type":"array","optional":"false"}],"return":{"type":"int","description":""},"errors":null,"notes":[{"type":"warning","description":"This function is\nEXPERIMENTAL. The behaviour of this function, its name, and\nsurrounding documentation may change without notice in a future release of PHP.\nThis function should be used at your own risk."}],"changelog":[],"seealso":[]}