{"name":"vpopmail_add_domain_ex","purpose":"Add a new virtual domain","manualid":"function.vpopmail-add-domain-ex","version":"PHP 4 >= 4.0.5, PECL vpopmail >= 0.2","params":[{"name":"domain","type":"string","optional":"false"},{"name":"passwd","type":"string","optional":"false"},{"name":"quota","type":"string","optional":"true"},{"name":"bounce","type":"string","optional":"true"},{"name":"apop","type":"bool","optional":"true"}],"return":{"type":"bool","description":null},"errors":null,"notes":[],"changelog":[],"seealso":[]}