{"name":"DateTimeZone.getTransitions","purpose":"Returns all transitions for the timezone","manualid":"datetimezone.gettransitions","version":false,"params":[{"name":"timestamp_begin","type":"int","optional":"true"},{"name":"timestamp_end","type":"int","optional":"true"},{"name":"object","type":"DateTimeZone","optional":"false"},{"name":"timestamp_begin","type":"int","optional":"true"},{"name":"timestamp_end","type":"int","optional":"true"}],"return":{"type":"array","description":"Returns numerically indexed array containing associative array with all\n   transitions on success or FALSE on failure."},"errors":null,"notes":[],"changelog":[{"version":"5.3.0","change":"The optional timestamp_begin and timestamp_end \n        were added."}],"seealso":[]}