{"name":"imageftbbox","purpose":"Give the bounding box of a text using fonts via freetype2","manualid":"function.imageftbbox","version":"PHP 4 >= 4.0.7, PHP 5","params":[{"name":"size","type":"float","optional":"false"},{"name":"angle","type":"float","optional":"false"},{"name":"fontfile","type":"string","optional":"false"},{"name":"text","type":"string","optional":"false"},{"name":"extrainfo","type":"array","optional":"true"}],"return":{"type":"array","description":"imageftbbox returns an array with 8\n   elements representing four points making the bounding box of the\n   text:\n   \n    \n     \n      \n       0\n       lower left corner, X position\n      \n      \n       1\n       lower left corner, Y position\n      \n      \n       2\n       lower right corner, X position\n      \n      \n       3\n       lower right corner, Y position\n      \n      \n       4\n       upper right corner, X position\n      \n      \n       5\n       upper right corner, Y position\n      \n      \n       6\n       upper left corner, X position\n      \n      \n       7\n       upper left corner, Y positionThe points are relative to the text regardless of the\n   angle, so \"upper left\" means in the top left-hand \n   corner seeing the text horizontally."},"errors":null,"notes":[{"type":"note","description":"This function requires GD 2.0.1 or later (2.0.28 or later is recommended)."},{"type":"note","description":"This function is only available if\nPHP is compiled with freetype support (--with-freetype-dir=DIR)"}],"changelog":[{"version":"4.3.5","change":"extrainfo was made optional."}],"seealso":[]}