{"name":"imagecolorexact","purpose":"Get the index of the specified color","manualid":"function.imagecolorexact","version":"PHP 4, PHP 5","params":[{"name":"image","type":"resource","optional":"false"},{"name":"red","type":"int","optional":"false"},{"name":"green","type":"int","optional":"false"},{"name":"blue","type":"int","optional":"false"}],"return":{"type":"int","description":"Returns the index of the specified color in the palette, or -1 if the\n   color does not exist."},"errors":null,"notes":[],"changelog":[],"seealso":[{"type":"function","name":"imagecolorclosest"}]}