{"name":"pg_last_notice","purpose":"Returns the last notice message from PostgreSQL server","manualid":"function.pg-last-notice","version":"PHP 4 >= 4.0.6, PHP 5","params":[{"name":"connection","type":"resource","optional":"false"}],"return":{"type":"string","description":"A string containing the last notice on the \n   given connection, or FALSE on error."},"errors":null,"notes":[],"changelog":[{"version":"4.3.0","change":"This function is now fully implemented. Earlier versions ignores\n        database connection parameter."},{"version":"4.3.0","change":"The pgsql.ignore_notice and \n        pgsql.log_notice php.ini directives were added."},{"version":"4.0.6","change":"PHP 4.0.6 has problem with notice message handling. Use of the\n        PostgreSQL module with PHP 4.0.6 is not recommended even if you are\n        not using pg_last_notice."}],"seealso":[{"type":"function","name":"pg_query"},{"type":"function","name":"pg_last_error"}]}