{"name":"odbc_statistics","purpose":"Retrieve statistics about a table","manualid":"function.odbc-statistics","version":"PHP 4, PHP 5","params":[{"name":"connection_id","type":"resource","optional":"false"},{"name":"qualifier","type":"string","optional":"false"},{"name":"owner","type":"string","optional":"false"},{"name":"table_name","type":"string","optional":"false"},{"name":"unique","type":"int","optional":"false"},{"name":"accuracy","type":"int","optional":"false"}],"return":{"type":"resource","description":"Returns an ODBC result identifier or FALSE on failure.The result set has the following columns:\n   \n    TABLE_QUALIFIER\n    TABLE_OWNER\n    TABLE_NAME\n    NON_UNIQUE\n    INDEX_QUALIFIER\n    INDEX_NAME\n    TYPE\n    SEQ_IN_INDEX\n    COLUMN_NAME\n    COLLATION\n    CARDINALITY\n    PAGES\n    FILTER_CONDITIONThe result set is ordered by NON_UNIQUE, TYPE, INDEX_QUALIFIER,\n   INDEX_NAME and SEQ_IN_INDEX."},"errors":null,"notes":[],"changelog":[],"seealso":[]}