{"name":"gupnp_context_host_path","purpose":"Start hosting","manualid":"function.gupnp-context-host-path","version":"PECL gupnp >= 0.1.0","params":[{"name":"context","type":"resource","optional":"false"},{"name":"local_path","type":"string","optional":"false"},{"name":"server_path","type":"string","optional":"false"}],"return":{"type":"bool","description":"Returns TRUE on success or FALSE on failure."},"errors":null,"notes":[],"changelog":[],"seealso":[{"type":"function","name":"gupnp_context_new"},{"type":"function","name":"gupnp_context_unhost_path"}]}