{"name":"mysqli.server_version","purpose":"Returns the version of the MySQL server as an integer","manualid":"mysqli.get-server-version","version":false,"params":[{"name":"link","type":"mysqli","optional":"false"}],"return":{"type":"int","description":"An integer representing the server version.The form of this version number is\n   main_version * 10000 + minor_version * 100 + sub_version\n   (i.e. version 4.1.0 is 40100)."},"errors":null,"notes":[],"changelog":[],"seealso":[{"type":"function","name":"mysqli_get_client_info"},{"type":"function","name":"mysqli_get_client_version"},{"type":"function","name":"mysqli_get_server_info"}]}