{"name":"stomp_ack","purpose":"Acknowledges consumption of a message","manualid":"stomp.ack","version":false,"params":[{"name":"msg","type":"mixed","optional":"false"},{"name":"headers","type":"array","optional":"true"},{"name":"link","type":"resource","optional":"false"},{"name":"msg","type":"mixed","optional":"false"},{"name":"headers","type":"array","optional":"true"}],"return":{"type":"bool","description":"Returns TRUE on success or FALSE on failure."},"errors":null,"notes":[{"type":"note","description":"A transaction header may be specified, indicating that the message acknowledgment should be part of the named transaction."},{"type":"tip","description":"Stomp is inherently asynchronous. Synchronous communication can be implemented adding a receipt header. This will cause methods to not return anything until the server has acknowledged receipt of the message or until read timeout was reached."}],"changelog":[],"seealso":[]}