{"name":"Memcache.getStats","purpose":"Get statistics of the server","manualid":"function.memcache-getstats","version":false,"params":[{"name":"type","type":"string","optional":"true"},{"name":"slabid","type":"int","optional":"true"},{"name":"limit","type":"int","optional":"true","initializer":"100"}],"return":{"type":"array","description":"Returns an associative array of server statistics or FALSE on failure."},"errors":null,"notes":[],"changelog":[],"seealso":[{"type":"function","name":"Memcache::getVersion"},{"type":"function","name":"Memcache::getExtendedStats"}]}