{"name":"Phar.delMetadata","purpose":"Deletes the global metadata of the phar","manualid":"phar.delmetadata","version":false,"params":[],"return":{"type":"bool","description":"returns TRUE on success, but it is better to check for thrown exception,\n   and assume success if none is thrown."},"errors":"Throws PharException if errors occur while flushing\n   changes to disk.","notes":[],"changelog":[],"seealso":[{"type":"function","name":"Phar::getMetadata"},{"type":"function","name":"Phar::setMetadata"},{"type":"function","name":"Phar::hasMetadata"}]}