{"name":"PDO.sqliteCreateFunction","purpose":"Registers a User Defined Function for use in SQL statements","manualid":"function.pdo-sqlitecreatefunction","version":false,"params":[{"name":"function_name","type":"string","optional":"false"},{"name":"callback","type":"callback","optional":"false"},{"name":"num_args","type":"int","optional":"true"}],"return":{"type":"bool","description":"Returns TRUE on success or FALSE on failure."},"errors":null,"notes":[],"changelog":[],"seealso":[{"type":false,"name":false},{"type":"function","name":"sqlite_create_function"},{"type":"function","name":"sqlite_create_aggregate"}]}