{"name":"streamWrapper.mkdir","purpose":"Create a directory","manualid":"streamwrapper.mkdir","version":false,"params":[{"name":"path","type":"string","optional":"false"},{"name":"mode","type":"int","optional":"false"},{"name":"options","type":"int","optional":"false"}],"return":{"type":"bool","description":"Returns TRUE on success or FALSE on failure."},"errors":"Emits\nE_WARNING if call to this method fails\n(i.e. not implemented).","notes":[{"type":"note","description":"The\nstreamWrapper->context\nproperty is updated if a valid context is passed to the caller function."}],"changelog":[],"seealso":[{"type":"function","name":"mkdir"},{"type":"methodname","name":"streamwrapper::rmdir"}]}