{"name":"xml_parser_get_option","purpose":"Get options from an XML parser","manualid":"function.xml-parser-get-option","version":"PHP 4, PHP 5","params":[{"name":"parser","type":"resource","optional":"false"},{"name":"option","type":"int","optional":"false"}],"return":{"type":"mixed","description":"This function returns FALSE if parser does\n   not refer to a valid parser or if option isn't\n   valid (generates also a E_WARNING).\n   Else the option's value is returned."},"errors":null,"notes":[],"changelog":[],"seealso":[]}