{"name":"xmlrpc_set_type","purpose":"Sets xmlrpc type, base64 or datetime, for a PHP string value","manualid":"function.xmlrpc-set-type","version":"PHP 4 >= 4.1.0, PHP 5","params":[{"name":"value","type":"string","optional":"false"},{"name":"type","type":"string","optional":"false"}],"return":{"type":"bool","description":"Returns TRUE on success or FALSE on failure.\n   If successful, value is converted to an object."},"errors":"Issues E_WARNING with type unsupported by XMLRPC.","notes":[],"changelog":[],"seealso":[]}